{
   "total":1,
   "data":[
      {
         "current_trial_status":"Active",
         "nct_id":"NCT04438382",
         "brief_title":"Infliximab and Intravenous Immunoglobulin Therapy in Treating Patients with Steroid-Refractory Pneumonitis",
         "eligibility":{
            "structured":{
               "max_age":"999 Years",
               "max_age_number":999,
               "min_age_unit":"Years",
               "max_age_unit":"Years",
               "max_age_in_years":999,
               "gender":"BOTH",
               "min_age":"18 Years",
               "min_age_number":18,
               "min_age_in_years":18
            }
         },
         "diseases":[
            {
               "inclusion_indicator":"TRIAL",
               "paths":null,
               "synonyms":[
                  "HEMOLYMPHORETICULAR TUMOR, MALIGNANT",
                  "Hematologic Cancer",
                  "Hematologic Malignancy",
                  "Hematologic Neoplasm",
                  "Hematological Neoplasm",
                  "Hematological Tumor",
                  "Hematopoietic Cancer",
                  "Hematopoietic Cell Tumor",
                  "Hematopoietic Neoplasm",
                  "Hematopoietic Neoplasms including Lymphomas",
                  "Hematopoietic Tumor",
                  "Hematopoietic and Lymphoid Neoplasms",
                  "Hematopoietic malignancy, NOS",
                  "Hematopoietic, Including Myeloma",
                  "Malignant Hematologic Neoplasm",
                  "Malignant Hematopoietic Neoplasm",
                  "hematologic cancer"
               ],
               "nci_thesaurus_concept_id":"C27134",
               "display_name":"Hematopoietic and Lymphoid Cell Neoplasm",
               "type":[
                  "maintype"
               ],
               "lead_disease_indicator":"YES",
               "preferred_name":"Hematopoietic and Lymphoid Cell Neoplasm",
               "parents":[
                  "C26323",
                  "C35813",
                  "C4741"
               ]
            },
            {
               "inclusion_indicator":"TRIAL",
               "paths":[
                  {
                     "concepts":[
                        {
                           "code":"C9292",
                           "label":"Solid Neoplasm",
                           "idx":0
                        }
                     ],
                     "direction":1
                  }
               ],
               "synonyms":[
                  "Malignant Solid Neoplasm"
               ],
               "nci_thesaurus_concept_id":"C132146",
               "display_name":"Malignant Solid Tumor",
               "type":[
                  "subtype"
               ],
               "lead_disease_indicator":"YES",
               "preferred_name":"Malignant Solid Neoplasm",
               "parents":[
                  "C9305",
                  "C9292"
               ]
            },
            {
               "inclusion_indicator":"TRIAL",
               "paths":[
                  {
                     "concepts":[
                        {
                           "code":"C2991",
                           "label":"Disease or Disorder",
                           "idx":0
                        }
                     ],
                     "direction":1
                  }
               ],
               "synonyms":[

               ],
               "nci_thesaurus_concept_id":"C156671",
               "display_name":"Steroid-Refractory Pneumonitis",
               "type":[
                  "subtype"
               ],
               "lead_disease_indicator":"NO",
               "preferred_name":"Steroid-Refractory Pneumonitis",
               "parents":[
                  "C113159"
               ]
            },
            {
               "inclusion_indicator":"TREE",
               "synonyms":[

               ],
               "nci_thesaurus_concept_id":"C35755",
               "display_name":"Non-Neoplastic Respiratory System Disorder",
               "type":[
                  "subtype"
               ],
               "lead_disease_indicator":"NO",
               "preferred_name":"Non-Neoplastic Respiratory System Disorder",
               "parents":[
                  "C53531",
                  "C26871"
               ]
            },
            {
               "inclusion_indicator":"TREE",
               "synonyms":[
                  "Solid Neoplasm",
                  "Solid tumor, NOS",
                  "solid tumor"
               ],
               "nci_thesaurus_concept_id":"C9292",
               "display_name":"Solid Tumor",
               "type":[
                  "maintype"
               ],
               "lead_disease_indicator":"YES",
               "preferred_name":"Solid Neoplasm",
               "parents":[
                  "C7062"
               ]
            },
            {
               "inclusion_indicator":"TREE",
               "synonyms":[
                  "Diagnosis",
                  "Disease",
                  "Disease or Disorder",
                  "Disease or Disorder, Non-Neoplastic",
                  "Diseases",
                  "Diseases and Disorders",
                  "Disorder",
                  "Disorders",
                  "condition",
                  "disease",
                  "disease term",
                  "disease_term",
                  "disorder"
               ],
               "nci_thesaurus_concept_id":"C2991",
               "display_name":"Other Disease",
               "type":[
                  "maintype"
               ],
               "lead_disease_indicator":"NO",
               "preferred_name":"Disease or Disorder",
               "parents":[
                  "C7057"
               ]
            },
            {
               "inclusion_indicator":"TREE",
               "synonyms":[
                  "Hematopoietic and Lymphoid System Disease"
               ],
               "nci_thesaurus_concept_id":"C35814",
               "display_name":"Hematopoietic and Lymphoid System Disorder",
               "type":[
                  "subtype"
               ],
               "lead_disease_indicator":"YES",
               "preferred_name":"Hematopoietic and Lymphoid System Disorder",
               "parents":[
                  "C27551"
               ]
            },
            {
               "inclusion_indicator":"TREE",
               "synonyms":[

               ],
               "nci_thesaurus_concept_id":"C3263",
               "display_name":"Neoplasm by Site",
               "type":[
                  "subtype"
               ],
               "lead_disease_indicator":"YES",
               "preferred_name":"Neoplasm by Site",
               "parents":[
                  "C3262"
               ]
            },
            {
               "inclusion_indicator":"TREE",
               "synonyms":[
                  "Blood Disease",
                  "Blood Disorder",
                  "Hematologic Disorder",
                  "Hematological Disorder"
               ],
               "nci_thesaurus_concept_id":"C26323",
               "display_name":"Hematologic and Lymphocytic Disorder",
               "type":[
                  "subtype"
               ],
               "lead_disease_indicator":"YES",
               "preferred_name":"Hematologic and Lymphocytic Disorder",
               "parents":[
                  "C35814"
               ]
            },
            {
               "inclusion_indicator":"TREE",
               "synonyms":[
                  "Disorder of Lung",
                  "Lung Disorders",
                  "Pulmonary Disease",
                  "Pulmonary Diseases",
                  "Pulmonary Disorder",
                  "Pulmonary Disorders"
               ],
               "nci_thesaurus_concept_id":"C3198",
               "display_name":"Lung Disorder",
               "type":[
                  "subtype"
               ],
               "lead_disease_indicator":"NO",
               "preferred_name":"Lung Disorder",
               "parents":[
                  "C26871",
                  "C35742"
               ]
            },
            {
               "inclusion_indicator":"TREE",
               "synonyms":[
                  "Thoracic Disease"
               ],
               "nci_thesaurus_concept_id":"C35742",
               "display_name":"Thoracic Disorder",
               "type":[
                  "subtype"
               ],
               "lead_disease_indicator":"NO",
               "preferred_name":"Thoracic Disorder",
               "parents":[
                  "C27669"
               ]
            },
            {
               "inclusion_indicator":"TREE",
               "synonyms":[
                  "Non-Neoplastic Thoracic Disease"
               ],
               "nci_thesaurus_concept_id":"C35743",
               "display_name":"Non-Neoplastic Thoracic Disorder",
               "type":[
                  "subtype"
               ],
               "lead_disease_indicator":"NO",
               "preferred_name":"Non-Neoplastic Thoracic Disorder",
               "parents":[
                  "C53531",
                  "C35742"
               ]
            },
            {
               "inclusion_indicator":"TREE",
               "synonyms":[

               ],
               "nci_thesaurus_concept_id":"C7062",
               "display_name":"Neoplasm by Special Category",
               "type":[
                  "subtype"
               ],
               "lead_disease_indicator":"YES",
               "preferred_name":"Neoplasm by Special Category",
               "parents":[
                  "C3262"
               ]
            },
            {
               "inclusion_indicator":"TREE",
               "synonyms":[
                  "Respiratory and Thoracic Disease",
                  "Respiratory, Thoracic, and Mediastinal Disease",
                  "Respiratory, Thoracic, and Mediastinal Disorder"
               ],
               "nci_thesaurus_concept_id":"C27669",
               "display_name":"Respiratory and Thoracic Disorder",
               "type":[
                  "subtype"
               ],
               "lead_disease_indicator":"NO",
               "preferred_name":"Respiratory and Thoracic Disorder",
               "parents":[
                  "C27551"
               ]
            },
            {
               "inclusion_indicator":"TREE",
               "synonyms":[
                  "CA",
                  "Cancer",
                  "Malignancy",
                  "Malignant Growth",
                  "Malignant Neoplastic Disease",
                  "Malignant Tumor",
                  "NEOPLASM, MALIGNANT",
                  "Neoplasm, malignant",
                  "Tumor, malignant, NOS",
                  "Unclassified tumor, malignant",
                  "cancer",
                  "malignancy"
               ],
               "nci_thesaurus_concept_id":"C9305",
               "display_name":"Malignant Neoplasm",
               "type":[
                  "subtype"
               ],
               "lead_disease_indicator":"YES",
               "preferred_name":"Malignant Neoplasm",
               "parents":[
                  "C7062"
               ]
            },
            {
               "inclusion_indicator":"TREE",
               "synonyms":[

               ],
               "nci_thesaurus_concept_id":"C113159",
               "display_name":"Pneumonitis",
               "type":[
                  "subtype"
               ],
               "lead_disease_indicator":"NO",
               "preferred_name":"Pneumonitis",
               "parents":[
                  "C27557"
               ]
            },
            {
               "inclusion_indicator":"TREE",
               "synonyms":[
                  "Tumor Morphology",
                  "Tumor_Morphology"
               ],
               "nci_thesaurus_concept_id":"C4741",
               "display_name":"Neoplasm by Morphology",
               "type":[
                  "subtype"
               ],
               "lead_disease_indicator":"YES",
               "preferred_name":"Neoplasm by Morphology",
               "parents":[
                  "C3262"
               ]
            },
            {
               "inclusion_indicator":"TREE",
               "synonyms":[
                  "Non-Neoplastic Pulmonary Disorder",
                  "Non-neoplastic Lung Disorders",
                  "Non-neoplastic Pulmonary Disease",
                  "Non-neoplastic Pulmonary Diseases"
               ],
               "nci_thesaurus_concept_id":"C27557",
               "display_name":"Non-Neoplastic Lung Disorder",
               "type":[
                  "subtype"
               ],
               "lead_disease_indicator":"NO",
               "preferred_name":"Non-Neoplastic Lung Disorder",
               "parents":[
                  "C3198",
                  "C35755",
                  "C35743"
               ]
            },
            {
               "inclusion_indicator":"TREE",
               "synonyms":[

               ],
               "nci_thesaurus_concept_id":"C7057",
               "display_name":"Disease, Disorder or Finding",
               "type":[

               ],
               "lead_disease_indicator":"NO",
               "preferred_name":"Disease, Disorder or Finding",
               "parents":[

               ]
            },
            {
               "inclusion_indicator":"TREE",
               "synonyms":[
                  "Disease by Site"
               ],
               "nci_thesaurus_concept_id":"C27551",
               "display_name":"Disorder by Site",
               "type":[
                  "subtype"
               ],
               "lead_disease_indicator":"NO",
               "preferred_name":"Disorder by Site",
               "parents":[
                  "C2991"
               ]
            },
            {
               "inclusion_indicator":"TREE",
               "synonyms":[
                  "Hematopoietic and Lymphoid System Tumor"
               ],
               "nci_thesaurus_concept_id":"C35813",
               "display_name":"Hematopoietic and Lymphoid System Neoplasm",
               "type":[
                  "subtype"
               ],
               "lead_disease_indicator":"YES",
               "preferred_name":"Hematopoietic and Lymphoid System Neoplasm",
               "parents":[
                  "C35814",
                  "C3263"
               ]
            },
            {
               "inclusion_indicator":"TREE",
               "synonyms":[
                  "Non-Neoplastic Disease by Site"
               ],
               "nci_thesaurus_concept_id":"C53531",
               "display_name":"Non-Neoplastic Disorder by Site",
               "type":[
                  "subtype"
               ],
               "lead_disease_indicator":"NO",
               "preferred_name":"Non-Neoplastic Disorder by Site",
               "parents":[
                  "C53529"
               ]
            },
            {
               "inclusion_indicator":"TREE",
               "synonyms":[

               ],
               "nci_thesaurus_concept_id":"C7057",
               "display_name":"Disease, Disorder or Finding",
               "type":[

               ],
               "lead_disease_indicator":"YES",
               "preferred_name":"Disease, Disorder or Finding",
               "parents":[

               ]
            },
            {
               "inclusion_indicator":"TREE",
               "synonyms":[
                  "Diagnosis",
                  "Disease",
                  "Disease or Disorder",
                  "Disease or Disorder, Non-Neoplastic",
                  "Diseases",
                  "Diseases and Disorders",
                  "Disorder",
                  "Disorders",
                  "condition",
                  "disease",
                  "disease term",
                  "disease_term",
                  "disorder"
               ],
               "nci_thesaurus_concept_id":"C2991",
               "display_name":"Other Disease",
               "type":[
                  "maintype"
               ],
               "lead_disease_indicator":"YES",
               "preferred_name":"Disease or Disorder",
               "parents":[
                  "C7057"
               ]
            },
            {
               "inclusion_indicator":"TREE",
               "synonyms":[
                  "Disorder of Respiratory System",
                  "Respiratory Disorder",
                  "Unspecified Respiratory Problem"
               ],
               "nci_thesaurus_concept_id":"C26871",
               "display_name":"Respiratory System Disorder",
               "type":[
                  "subtype"
               ],
               "lead_disease_indicator":"NO",
               "preferred_name":"Respiratory System Disorder",
               "parents":[
                  "C27669"
               ]
            },
            {
               "inclusion_indicator":"TREE",
               "synonyms":[
                  "NON-NEOPLASTIC",
                  "Non-Neoplastic Disease",
                  "Non-neoplastic Disorder",
                  "Non-neoplastic condition, NOS",
                  "Non-neoplastic disorder, NOS"
               ],
               "nci_thesaurus_concept_id":"C53529",
               "display_name":"Non-Neoplastic Disorder",
               "type":[
                  "subtype"
               ],
               "lead_disease_indicator":"NO",
               "preferred_name":"Non-Neoplastic Disorder",
               "parents":[
                  "C2991"
               ]
            },
            {
               "inclusion_indicator":"TREE",
               "synonyms":[
                  "Disease by Site"
               ],
               "nci_thesaurus_concept_id":"C27551",
               "display_name":"Disorder by Site",
               "type":[
                  "subtype"
               ],
               "lead_disease_indicator":"YES",
               "preferred_name":"Disorder by Site",
               "parents":[
                  "C2991"
               ]
            },
            {
               "inclusion_indicator":"TREE",
               "synonyms":[
                  "Neoplasia",
                  "Neoplasm",
                  "Neoplasm, NOS",
                  "Neoplasms, NOS",
                  "Neoplastic Disease",
                  "Neoplastic Growth",
                  "Tumor, NOS",
                  "neoplasia",
                  "neoplasm",
                  "tumor"
               ],
               "nci_thesaurus_concept_id":"C3262",
               "display_name":"Other Neoplasm",
               "type":[
                  "maintype"
               ],
               "lead_disease_indicator":"YES",
               "preferred_name":"Neoplasm",
               "parents":[
                  "C2991"
               ]
            }
         ],
         "nci_id":"NCI-2018-02825"
      }
   ]
}
